LICENSE.txt
README.md
cloudnotificationmessage.py
test.py
validate_schema.py
podaac_cloud_notification_message_schema.egg-info/PKG-INFO
podaac_cloud_notification_message_schema.egg-info/SOURCES.txt
podaac_cloud_notification_message_schema.egg-info/dependency_links.txt
podaac_cloud_notification_message_schema.egg-info/requires.txt
podaac_cloud_notification_message_schema.egg-info/top_level.txt
podaac_cloud_notification_message_schema-1.6.1.dist-info/LICENSE.txt
podaac_cloud_notification_message_schema-1.6.1.dist-info/METADATA
podaac_cloud_notification_message_schema-1.6.1.dist-info/WHEEL
podaac_cloud_notification_message_schema-1.6.1.dist-info/top_level.txt
podaac_cloud_notification_message_schema-1.6.1.dist-info/RECORD
